setup.py
cipher_crns/__init__.py
cipher_crns/affinecipher.py
cipher_crns/caesarcipher.py
cipher_crns/hillcipher.py
cipher_crns/playfair.py
crns_cipher.egg-info/PKG-INFO
crns_cipher.egg-info/SOURCES.txt
crns_cipher.egg-info/dependency_links.txt
crns_cipher.egg-info/requires.txt
crns_cipher.egg-info/top_level.txt