Metadata-Version: 1.0
Name: crns-cipher
Version: 0.1
Summary: Ciphers
Home-page: UNKNOWN
Author: Nirav Shah
Author-email: 15ce128@charusat.edu.in
License: MIT
Platform: UNKNOWN
